{
  "movies": [
    {"movie_id": 1, "title": "Inception", "release_year": 2010, "duration_minutes": 148, "director_name": "Christopher Nolan", "studio_name": "Warner Bros."},
    {"movie_id": 2, "title": "The Shawshank Redemption", "release_year": 1994, "duration_minutes": 142, "director_name": "Frank Darabont", "studio_name": "Columbia Pictures"},
    {"movie_id": 3, "title": "Pulp Fiction", "release_year": 1994, "duration_minutes": 154, "director_name": "Quentin Tarantino", "studio_name": "Miramax Films"},
    {"movie_id": 4, "title": "The Dark Knight", "release_year": 2008, "duration_minutes": 152, "director_name": "Christopher Nolan", "studio_name": "Warner Bros."},
    {"movie_id": 5, "title": "Forrest Gump", "release_year": 1994, "duration_minutes": 142, "director_name": "Robert Zemeckis", "studio_name": "Paramount Pictures"},
    {"movie_id": 6, "title": "Interstellar", "release_year": 2014, "duration_minutes": 169, "director_name": "Christopher Nolan", "studio_name": "Warner Bros."},
    {"movie_id": 7, "title": "The Matrix", "release_year": 1999, "duration_minutes": 136, "director_name": "The Wachowskis", "studio_name": "Warner Bros."},
    {"movie_id": 8, "title": "Fight Club", "release_year": 1999, "duration_minutes": 139, "director_name": "David Fincher", "studio_name": "20th Century Fox"},
    {"movie_id": 9, "title": "Goodfellas", "release_year": 1990, "duration_minutes": 146, "director_name": "Martin Scorsese", "studio_name": "Warner Bros."},
    {"movie_id": 10, "title": "The Godfather", "release_year": 1972, "duration_minutes": 175, "director_name": "Francis Ford Coppola", "studio_name": "Paramount Pictures"},
    {"movie_id": 11, "title": "Schindler's List", "release_year": 1993, "duration_minutes": 195, "director_name": "Steven Spielberg", "studio_name": "Universal Pictures"},
    {"movie_id": 12, "title": "Saving Private Ryan", "release_year": 1998, "duration_minutes": 169, "director_name": "Steven Spielberg", "studio_name": "DreamWorks"},
    {"movie_id": 13, "title": "The Silence of the Lambs", "release_year": 1991, "duration_minutes": 118, "director_name": "Jonathan Demme", "studio_name": "Orion Pictures"},
    {"movie_id": 14, "title": "Se7en", "release_year": 1995, "duration_minutes": 127, "director_name": "David Fincher", "studio_name": "New Line Cinema"},
    {"movie_id": 15, "title": "Gladiator", "release_year": 2000, "duration_minutes": 155, "director_name": "Ridley Scott", "studio_name": "DreamWorks"}
  ],
  "actors": [
    {"actor_id": 1, "name": "Leonardo DiCaprio", "nationality": "USA"},
    {"actor_id": 2, "name": "Joseph Gordon-Levitt", "nationality": "USA"},
    {"actor_id": 3, "name": "Ellen Page", "nationality": "Canada"},
    {"actor_id": 4, "name": "Tim Robbins", "nationality": "USA"},
    {"actor_id": 5, "name": "Morgan Freeman", "nationality": "USA"},
    {"actor_id": 6, "name": "John Travolta", "nationality": "USA"},
    {"actor_id": 7, "name": "Uma Thurman", "nationality": "USA"},
    {"actor_id": 8, "name": "Samuel L. Jackson", "nationality": "USA"},
    {"actor_id": 9, "name": "Christian Bale", "nationality": "UK"},
    {"actor_id": 10, "name": "Heath Ledger", "nationality": "Australia"},
    {"actor_id": 11, "name": "Tom Hanks", "nationality": "USA"},
    {"actor_id": 12, "name": "Robin Wright", "nationality": "USA"},
    {"actor_id": 13, "name": "Matthew McConaughey", "nationality": "USA"},
    {"actor_id": 14, "name": "Anne Hathaway", "nationality": "USA"},
    {"actor_id": 15, "name": "Keanu Reeves", "nationality": "Canada"},
    {"actor_id": 16, "name": "Laurence Fishburne", "nationality": "USA"},
    {"actor_id": 17, "name": "Brad Pitt", "nationality": "USA"},
    {"actor_id": 18, "name": "Edward Norton", "nationality": "USA"},
    {"actor_id": 19, "name": "Robert De Niro", "nationality": "USA"},
    {"actor_id": 20, "name": "Joe Pesci", "nationality": "USA"},
    {"actor_id": 21, "name": "Marlon Brando", "nationality": "USA"},
    {"actor_id": 22, "name": "Al Pacino", "nationality": "USA"},
    {"actor_id": 23, "name": "Liam Neeson", "nationality": "Ireland"},
    {"actor_id": 24, "name": "Ben Kingsley", "nationality": "UK"},
    {"actor_id": 25, "name": "Matt Damon", "nationality": "USA"},
    {"actor_id": 26, "name": "Jodie Foster", "nationality": "USA"},
    {"actor_id": 27, "name": "Anthony Hopkins", "nationality": "UK"},
    {"actor_id": 28, "name": "Gwyneth Paltrow", "nationality": "USA"},
    {"actor_id": 29, "name": "Russell Crowe", "nationality": "New Zealand"},
    {"actor_id": 30, "name": "Joaquin Phoenix", "nationality": "USA"}
  ],
  "directors": [
    {"director_id": 1, "name": "Christopher Nolan", "birth_year": 1970},
    {"director_id": 2, "name": "Frank Darabont", "birth_year": 1959},
    {"director_id": 3, "name": "Quentin Tarantino", "birth_year": 1963},
    {"director_id": 4, "name": "Robert Zemeckis", "birth_year": 1952},
    {"director_id": 5, "name": "The Wachowskis", "birth_year": 1965},
    {"director_id": 6, "name": "David Fincher", "birth_year": 1962},
    {"director_id": 7, "name": "Martin Scorsese", "birth_year": 1942},
    {"director_id": 8, "name": "Francis Ford Coppola", "birth_year": 1939},
    {"director_id": 9, "name": "Steven Spielberg", "birth_year": 1946},
    {"director_id": 10, "name": "Jonathan Demme", "birth_year": 1944},
    {"director_id": 11, "name": "Ridley Scott", "birth_year": 1937},
    {"director_id": 12, "name": "Denis Villeneuve", "birth_year": 1967},
    {"director_id": 13, "name": "Alfonso Cuaron", "birth_year": 1961},
    {"director_id": 14, "name": "James Cameron", "birth_year": 1954},
    {"director_id": 15, "name": "Peter Jackson", "birth_year": 1961}
  ],
  "genres": [
    {"genre_id": 1, "name": "Action"},
    {"genre_id": 2, "name": "Drama"},
    {"genre_id": 3, "name": "Thriller"},
    {"genre_id": 4, "name": "Sci-Fi"},
    {"genre_id": 5, "name": "Crime"},
    {"genre_id": 6, "name": "Romance"},
    {"genre_id": 7, "name": "Horror"},
    {"genre_id": 8, "name": "Comedy"},
    {"genre_id": 9, "name": "War"},
    {"genre_id": 10, "name": "Biography"},
    {"genre_id": 11, "name": "Mystery"},
    {"genre_id": 12, "name": "Adventure"}
  ],
  "countries": [
    {"country_id": 1, "name": "USA", "iso_code": "US"},
    {"country_id": 2, "name": "United Kingdom", "iso_code": "GB"},
    {"country_id": 3, "name": "France", "iso_code": "FR"},
    {"country_id": 4, "name": "Germany", "iso_code": "DE"},
    {"country_id": 5, "name": "Italy", "iso_code": "IT"},
    {"country_id": 6, "name": "Canada", "iso_code": "CA"},
    {"country_id": 7, "name": "Australia", "iso_code": "AU"},
    {"country_id": 8, "name": "Japan", "iso_code": "JP"},
    {"country_id": 9, "name": "South Korea", "iso_code": "KR"},
    {"country_id": 10, "name": "Spain", "iso_code": "ES"}
  ],
  "studios": [
    {"studio_id": 1, "name": "Warner Bros.", "founded_year": 1923},
    {"studio_id": 2, "name": "Columbia Pictures", "founded_year": 1924},
    {"studio_id": 3, "name": "Miramax Films", "founded_year": 1979},
    {"studio_id": 4, "name": "Paramount Pictures", "founded_year": 1912},
    {"studio_id": 5, "name": "20th Century Fox", "founded_year": 1935},
    {"studio_id": 6, "name": "Universal Pictures", "founded_year": 1912},
    {"studio_id": 7, "name": "DreamWorks", "founded_year": 1994},
    {"studio_id": 8, "name": "Orion Pictures", "founded_year": 1978},
    {"studio_id": 9, "name": "New Line Cinema", "founded_year": 1967},
    {"studio_id": 10, "name": "Lionsgate", "founded_year": 1997}
  ],
  "metadata": {
    "exported_at": "2025-01-01T00:00:00",
    "source": "PostgreSQL @ db.kii.pef.czu.cz",
    "tables": 6,
    "total_records": 92
  }
}
